COPYING.txt
MANIFEST.in
README.md
README.txt
setup.py
pydynamo/__init__.py
pydynamo/admin.py
pydynamo/app_settings.py
pydynamo/botobase.py
pydynamo/exception.py
pydynamo/fields.py
pydynamo/models.py
pydynamo/tests.py
pydynamo/views.py
pydynamo.egg-info/PKG-INFO
pydynamo.egg-info/SOURCES.txt
pydynamo.egg-info/dependency_links.txt
pydynamo.egg-info/requires.txt
pydynamo.egg-info/top_level.txt