Metadata-Version: 1.1
Name: pydynamo
Version: 0.1.4
Summary: Python library for communicating with dynamo db !
Home-page: http://github.com/nidhi-delhivery/pydynamo
Author: Nidhi Mittal
Author-email: mittalnidhi.mittal@gmail.com
License: LICENSE.txt
Platform: UNKNOWN
Classifier: Programming Language :: Python
Classifier: Programming Language :: Python :: 2.7
Classifier: License :: OSI Approved :: GNU General Public License (GPL)
Classifier: Operating System :: OS Independent
Classifier: Development Status :: 1 - Planning
Classifier: Environment :: Console
Classifier: Intended Audience :: Science/Research
Classifier: Topic :: Scientific/Engineering :: GIS
